mlflowops/__init__.py
mlflowops/mlflowops.py
mlflowops/session.py
mlflowops-0.1.2.dist-info/LICENSE
mlflowops-0.1.2.dist-info/METADATA
mlflowops-0.1.2.dist-info/WHEEL
mlflowops-0.1.2.dist-info/RECORD
