Metadata-Version: 2.1
Name: mlflowops
Version: 0.1.2
Summary: MLOps utils with MLFlow
License: MIT
Author: Carlos D. Escobar-Valbuena
Author-email: carlosdavidescobar@gmail.com
Requires-Python: >=3.8,<4.0
Classifier: License :: OSI Approved :: MIT License
Classifier: Programming Language :: Python :: 3
Classifier: Programming Language :: Python :: 3.8
Classifier: Programming Language :: Python :: 3.9
Classifier: Programming Language :: Python :: 3.10
Classifier: Programming Language :: Python :: 3.11
Requires-Dist: azure-ai-ml (>=1.8.0,<2.0.0)
Requires-Dist: mlflow (>=2.5.0,<3.0.0)
Requires-Dist: pandas (>=2.0.3,<3.0.0)
Requires-Dist: pydantic (>=2.0.3,<3.0.0)
Requires-Dist: python-dotenv (>=1.0.0,<2.0.0)
